example_pkg/__init__.py
nested_dictionaries/__init__.py
nested_dictionaries/nesteddict.py
nested_dictionary/__init__.py
nested_dictionary/my_module.py
nested_dictionaries-0.0.1.dist-info/LICENSE
nested_dictionaries-0.0.1.dist-info/METADATA
nested_dictionaries-0.0.1.dist-info/WHEEL
nested_dictionaries-0.0.1.dist-info/top_level.txt
nested_dictionaries-0.0.1.dist-info/RECORD
