Metadata-Version: 2.1
Name: nested-dictionaries
Version: 0.0.1
Summary: Nested Dictionaries
Home-page: https://github.com/LiNuXaDDiKt/python_nested_dictionaries
Author: Robert Poirier
Author-email: linuxaddikt@robsarea.com
License: UNKNOWN
Platform: UNKNOWN
Classifier: Programming Language :: Python :: 3
Classifier: License :: OSI Approved :: MIT License
Classifier: Operating System :: OS Independent
Requires-Python: >=3.4
